biobank/__init__.py
biobank/biobank_backend.py
biobank/conf/__init__.py
biobank/conf/settings.py
biobank/models/__init__.py
biobank/models/question.py
biobank_python_hooks-0.1.5.dist-info/DESCRIPTION.rst
biobank_python_hooks-0.1.5.dist-info/METADATA
biobank_python_hooks-0.1.5.dist-info/RECORD
biobank_python_hooks-0.1.5.dist-info/WHEEL
biobank_python_hooks-0.1.5.dist-info/metadata.json
biobank_python_hooks-0.1.5.dist-info/top_level.txt
