Metadata-Version: 2.0
Name: biobank-python-hooks
Version: 0.1.5
Summary: Hooks to allow system to integrate with PHP Biobank server
Home-page: https://bitbucket.org/lshtmweb/biobank-python-tools
Author: LSHTM Web
Author-email: webteam@lshtm.ac.uk
License: TBC
Keywords: kobotoolbox ona cureme
Platform: UNKNOWN
Classifier: Development Status :: 3 - Alpha
Classifier: Intended Audience :: Developers
Classifier: Topic :: Utilities
Classifier: License :: OSI Approved :: MIT License
Classifier: Framework :: Django
Classifier: Programming Language :: Python :: 2
Classifier: Programming Language :: Python :: 2.6
Classifier: Programming Language :: Python :: 2.7
Classifier: Programming Language :: Python :: 3
Classifier: Programming Language :: Python :: 3.2
Classifier: Programming Language :: Python :: 3.3
Classifier: Programming Language :: Python :: 3.4
Requires-Dist: Django (>=1.4)
Requires-Dist: requests
Requires-Dist: django-rest-hooks
